{"sections":{"16321237356a896dad":{"type":"slide-show","blocks":{"image_UDFC98":{"type":"image","settings":{"alignment":"left","enable_custom_position":false,"custom_horizontal":"","custom_vertical":"","enable_position_outside_image":false,"text_alignment":"left","enable_border_line":false,"padding_vertical":30,"content_width":600,"bg_color_content":"","border_color_content":"","profile_name":"","profile_name_color":"","profile_name_fs":20,"profile_name_fs_mb":20,"profile_name_fw":"normal","profile_title":"","profile_title_color":"","profile_title_fs":20,"profile_title_fs_mb":20,"profile_title_fw":"normal","profile_spacing_bottom":50,"sub_heading":"","letter_spacing_sub_title":"","font_size_sub_heading":30,"sub_heading_spacing_bottom":20,"font_weight_sub_heading":"400","border_sub_heading":"none","sub_title_position":"sub_title_above","color_sub_heading":"#ffffff","heading":"Heading","letter_spacing_heading":"","enable_border_heading":false,"font_style_heading":"normal","font_size_heading":60,"line_height_heading":60,"heading_spacing_bottom":35,"color_heading":"{{ shop.brand.colors.secondary[0].foreground }}","slide-des":"Description","font_size_des":20,"des_spacing_bottom":35,"color_des":"#ffffff","sub_heading_mb":"","font_size_sub_heading_mb":20,"sub_heading_spacing_bottom_mb":20,"font_weight_sub_heading_mb":"400","border_sub_heading_mb":"none","color_sub_heading_mb":"#ffffff","heading_mb":"","font_style_heading_mb":"normal","font_size_heading_mb":35,"line_height_heading_mb":35,"heading_spacing_bottom_mb":8,"color_heading_mb":"#ffffff","slide-des-mb":"","font_size_des_mb":12,"des_spacing_bottom_mb":35,"color_des_mb":"#ffffff","enable_icon_button":false,"button_slide":"Learn More","link":"shopify:\/\/pages\/about-us","button_slide_2":"","link_2":"","min_width_banner_button":100,"color_button":"#ffffff","border_button":"{{ shop.brand.colors.secondary[0].foreground }}","bg_button":"#232323","bg_button_gradient":"","color_button_hover":"{{ shop.brand.colors.secondary[0].foreground }}","border_button_hover":"{{ shop.brand.colors.secondary[0].foreground }}","bg_button_hover":"rgba(0,0,0,0)","bg_button_gradient_hover":"","lb_product_1":"","top_position_1":"10","left_position_1":"10","dots_color_1":"#ffffff","dots_bg_color_1":"#232323","dots_shadow_color_1":"#232323","lb_product_2":"","top_position_2":"10","left_position_2":"10","dots_color_2":"#ffffff","dots_bg_color_2":"#232323","dots_shadow_color_2":"#232323","lb_product_3":"","top_position_3":"10","left_position_3":"10","dots_color_3":"#ffffff","dots_bg_color_3":"#232323","dots_shadow_color_3":"#232323"}},"image_6rWb9N":{"type":"image","settings":{"alignment":"left","enable_custom_position":false,"custom_horizontal":"","custom_vertical":"","enable_position_outside_image":false,"text_alignment":"left","enable_border_line":false,"padding_vertical":30,"content_width":600,"bg_color_content":"","border_color_content":"","profile_name":"","profile_name_color":"","profile_name_fs":20,"profile_name_fs_mb":20,"profile_name_fw":"normal","profile_title":"","profile_title_color":"","profile_title_fs":20,"profile_title_fs_mb":20,"profile_title_fw":"normal","profile_spacing_bottom":50,"sub_heading":"","letter_spacing_sub_title":"","font_size_sub_heading":30,"sub_heading_spacing_bottom":20,"font_weight_sub_heading":"400","border_sub_heading":"none","sub_title_position":"sub_title_above","color_sub_heading":"#ffffff","heading":"Heading","letter_spacing_heading":"","enable_border_heading":false,"font_style_heading":"normal","font_size_heading":60,"line_height_heading":60,"heading_spacing_bottom":35,"color_heading":"{{ shop.brand.colors.secondary[0].foreground }}","slide-des":"","font_size_des":20,"des_spacing_bottom":35,"color_des":"#ffffff","sub_heading_mb":"","font_size_sub_heading_mb":20,"sub_heading_spacing_bottom_mb":20,"font_weight_sub_heading_mb":"400","border_sub_heading_mb":"none","color_sub_heading_mb":"#ffffff","heading_mb":"Heading","font_style_heading_mb":"normal","font_size_heading_mb":35,"line_height_heading_mb":35,"heading_spacing_bottom_mb":8,"color_heading_mb":"#ffffff","slide-des-mb":"Description","font_size_des_mb":12,"des_spacing_bottom_mb":35,"color_des_mb":"#ffffff","enable_icon_button":false,"button_slide":"Learn More","link":"shopify:\/\/pages\/about-us","button_slide_2":"","link_2":"","min_width_banner_button":100,"color_button":"#000000","border_button":"{{ shop.brand.colors.secondary[0].foreground }}","bg_button":"#232323","bg_button_gradient":"","color_button_hover":"{{ shop.brand.colors.secondary[0].foreground }}","border_button_hover":"{{ shop.brand.colors.secondary[0].foreground }}","bg_button_hover":"rgba(0,0,0,0)","bg_button_gradient_hover":"","lb_product_1":"","top_position_1":"10","left_position_1":"10","dots_color_1":"#ffffff","dots_bg_color_1":"#232323","dots_shadow_color_1":"#232323","lb_product_2":"","top_position_2":"10","left_position_2":"10","dots_color_2":"#ffffff","dots_bg_color_2":"#232323","dots_shadow_color_2":"#232323","lb_product_3":"","top_position_3":"10","left_position_3":"10","dots_color_3":"#ffffff","dots_bg_color_3":"#232323","dots_shadow_color_3":"#232323"}}},"block_order":["image_UDFC98","image_6rWb9N"],"custom_css":[],"settings":{"container":"fullwidth","padding_full_width":0,"mg_top_desktop":0,"mg_top_tablet":0,"mg_top_mobile":0,"mg_bottom_desktop":0,"mg_bottom_tablet":0,"mg_bottom_mobile":0,"slideshow_background":"","slideshow_background_gradient":"","autoplay":true,"slideshow_speed":"5000","slideshow_transition":"false","dots":"true","dots_color":"#e8e8e8","dots_border_color":"rgba(0,0,0,0)","dots_active_color":"#232323","dots_active_border_color":"rgba(0,0,0,0)","dots_direction":"bottom","position_slick_dots":"25px","dots_opacity":true,"arrow_active":false,"enable_custom_arrow":false,"arrow_width":35,"arrow_height":35,"arrow_size_icon":17,"arrow_color":"#ffffff","arrow_border_color":"rgba(0,0,0,0)","arrow_bg_color":"rgba(0,0,0,0)","arrow_color_hover":"","arrow_border_color_hover":"","arrow_bg_color_hover":"","position_slick_arrow":"10%","position_vertical_slick_arrow":"10%","video_height":"50%","auto_playvideo":true,"enable_categories":false,"text_categories":"Shop by categories","title_color":"#ffffff","bg_title":"#fd6506","text_icon_color":"#202020","menu_category":"","enable_banner":false,"lookbook_style":"1","lookbook_gradient_color":"","lookbook_background_color":"rgba(0,0,0,0)","lookbook_text_color":"#ffffff","lookbook_dots_enabled":false,"lookbook_show_by_default":false,"lookbook_dots_mobile_enabled":false,"show_lookbook_title_price":false}},"column_grid_VDzQYy":{"type":"column-grid","blocks":{"image_BXU4VU":{"type":"image","settings":{"col_bg":"rgba(0,0,0,0)","margin_bottom_image":0,"image_border_radius":0,"enable_border":false,"border_radius":4,"border_color":"#e2e5e7","border_color_hover":"#2d2d2d","text_position":"left","title":"Colletion","line-style-on":false,"color_text_col":"#1d1d1d","color_text_hover":"#3c3c3c","margin_bottom_title":0,"description":"","color_des":"#1d1d1d","link-button-on":true,"link-button-text":"View Collection","link":"shopify:\/\/collections\/stud-bite","link-button-icon":true,"link-button-padding":"0px","box_shadow":"none","bx_horizontal_length":0,"bx_vertical_length":3,"bx_blur_radius":8,"bx_spread":0,"bx_opacity":0.2,"bx_inset":"no"}},"image_fq7Xi7":{"type":"image","settings":{"col_bg":"rgba(0,0,0,0)","margin_bottom_image":0,"image_border_radius":0,"enable_border":false,"border_radius":4,"border_color":"#e2e5e7","border_color_hover":"#2d2d2d","text_position":"left","title":"Colletion","line-style-on":false,"color_text_col":"#1d1d1d","color_text_hover":"#3c3c3c","margin_bottom_title":0,"description":"","color_des":"#1d1d1d","link-button-on":true,"link-button-text":"View Collection","link":"shopify:\/\/collections\/stud-bite","link-button-icon":true,"link-button-padding":"0px","box_shadow":"none","bx_horizontal_length":0,"bx_vertical_length":3,"bx_blur_radius":8,"bx_spread":0,"bx_opacity":0.2,"bx_inset":"no"}},"image_JpkeC3":{"type":"image","settings":{"col_bg":"rgba(0,0,0,0)","margin_bottom_image":0,"image_border_radius":0,"enable_border":false,"border_radius":4,"border_color":"#e2e5e7","border_color_hover":"#2d2d2d","text_position":"left","title":"Colletion","line-style-on":false,"color_text_col":"#1d1d1d","color_text_hover":"#3c3c3c","margin_bottom_title":0,"description":"","color_des":"#1d1d1d","link-button-on":true,"link-button-text":"View Collection","link":"shopify:\/\/collections\/stud-bite","link-button-icon":true,"link-button-padding":"0px","box_shadow":"none","bx_horizontal_length":0,"bx_vertical_length":3,"bx_blur_radius":8,"bx_spread":0,"bx_opacity":0.2,"bx_inset":"no"}}},"block_order":["image_BXU4VU","image_fq7Xi7","image_JpkeC3"],"settings":{"section-id":"ranges","container":"container","padding_full_width":0,"mg_top_desktop":90,"mg_top_tablet":50,"mg_top_mobile":50,"mg_bottom_desktop":100,"mg_bottom_tablet":50,"mg_bottom_mobile":50,"brands_block_style":"style_1","enable_icons":true,"brand_layout":"grid","brand_bg":"rgba(0,0,0,0)","brand_bg_gradient":"","brand_title":"View Our Ranges","title_alignment":"center","color_title":"{{ shop.brand.colors.secondary[0].background }}","fontsize_title":32,"fontsize_title_mb":24,"mg_bottom_title":30,"enable_border_title":false,"border_color_title":"{{ shop.brand.colors.secondary[0].background }}","brand_des":"","color_des":"#1d1d1d","fontsize_des":18,"mg_bottom_des":0,"btn_text":"","fontsize_btn":12,"btn_spacing_top":15,"btn_link":"","btn_color":"#000000","main_btn_color":"rgba(0,0,0,0)","main_btn_color_hover":"rgba(0,0,0,0)","second_butt":false,"sec_btn_text":"","sec_btn_link":"","sec_btn_color":"#ffffff","sec_main_btn_color":"{{ shop.brand.colors.secondary[0].background }}","sec_main_btn_color_hover":"{{ shop.brand.colors.secondary[0].background }}","item_distance":20,"title_align":"center","col-radius":0,"brand_rows":"3","col_btn_color":"#ffffff","col_main_btn_color":"#000000","col_main_btn_color_hover":"#919191","fontsize_text":24,"fontsize_text_mb":18,"font_weight_title":"600","enable_arrows":true,"enable_dots":false,"style_position_arrows":"none","position_horizontal_arrow":15,"color_arrow":"","arrow_background":"","arrow_background_gradient":"","arrow_border":"","color_arrow_hover":"","arrow_background_hover":"","arrow_background_gradient_hover":"","arrow_border_hover":"","brand_rows_mb":"1","enable_hover_zoom_image":false}},"custom_cta_m8BjgC":{"type":"custom-cta","settings":{"cta_sec_id":"","fullwidths":true,"margin_top":0,"margin_bottom":0,"padding_top":0,"padding_bottom":30,"cta_text_title":"Title","title_margin_bot":20,"cta_texts":"<p>Description<\/p>","cta_texts_font_size":18,"cta_texts_color":"#141006","cta_button_text":"Enquire now","cta_button_link":"shopify:\/\/pages\/contact-us","btn_margin_top":25}},"17296510480ec9458f":{"type":"apps","blocks":{"shop_quiz_product_recommender_inline_quiz_AXYJgT":{"type":"shopify:\/\/apps\/shop-quiz-product-recommender\/blocks\/inline-quiz\/672f3d48-fd3b-4227-8778-c6e58c4f8a98","settings":{"quiz_id":"W0HXjzy","quiz_height":600,"quiz_autoscroll":true,"quiz_fixed_height":false}}},"block_order":["shop_quiz_product_recommender_inline_quiz_AXYJgT"],"settings":{"include_margins":false}},"video_block_FFnUpA":{"type":"video-block","settings":{"custom-css":"","container":"container","mg_top_desktop":50,"mg_top_tablet":50,"mg_top_mobile":50,"mg_bottom_desktop":50,"mg_bottom_tablet":50,"mg_bottom_mobile":50,"spotlight_bg":"#ffffff","spotlight_bg_gradient":"","video_block_title":"Video","color_title":"#232323","border-theme":"red","fontsize_title":16,"fontsize_title_mb":22,"margin_bottom_title":45,"video_block_des":"","color_des":"#3c3c3c","fontsize_des":16,"title_align":"center","autoplay":true,"video_height":"54","style_video":"youtube","video_url":"https:\/\/www.youtube.com\/watch?v=XIMLoLxmTDw","url_mp4":"","description":"","full_width":false}},"column_grid_km3BJi":{"type":"column-grid","blocks":{"image_whMQti":{"type":"image","settings":{"col_bg":"rgba(0,0,0,0)","margin_bottom_image":0,"image_border_radius":0,"enable_border":false,"border_radius":4,"border_color":"#e2e5e7","border_color_hover":"#2d2d2d","text_position":"left","title":"Title","line-style-on":false,"color_text_col":"#ffffff","color_text_hover":"#3e8cc4","margin_bottom_title":0,"description":"<ul><li>Lorem Ipsum<\/li><li>Lorem Ipsum<\/li><li>Lorem Ipsum<\/li><li>Lorem Ipsum<\/li><li>Lorem Ipsum<\/li><li>Lorem Ipsum<\/li><\/ul>","color_des":"#ffffff","link-button-on":false,"link-button-text":"","link":"","link-button-icon":false,"link-button-padding":"","box_shadow":"none","bx_horizontal_length":0,"bx_vertical_length":3,"bx_blur_radius":8,"bx_spread":0,"bx_opacity":0.2,"bx_inset":"no"}},"image_wQJKez":{"type":"image","settings":{"col_bg":"rgba(0,0,0,0)","margin_bottom_image":0,"image_border_radius":0,"enable_border":false,"border_radius":4,"border_color":"#e2e5e7","border_color_hover":"#2d2d2d","text_position":"left","title":"Title","line-style-on":false,"color_text_col":"#ffffff","color_text_hover":"#3e8cc4","margin_bottom_title":0,"description":"<ul><li>Lorem Ipsum<\/li><li>Lorem Ipsum<\/li><li>Lorem Ipsum<\/li><li>Lorem Ipsum<\/li><li>Lorem Ipsum<\/li><li>Lorem Ipsum<\/li><\/ul>","color_des":"#ffffff","link-button-on":false,"link-button-text":"","link":"","link-button-icon":false,"link-button-padding":"","box_shadow":"none","bx_horizontal_length":0,"bx_vertical_length":3,"bx_blur_radius":8,"bx_spread":0,"bx_opacity":0.2,"bx_inset":"no"}},"image_9QpB3f":{"type":"image","settings":{"col_bg":"rgba(0,0,0,0)","margin_bottom_image":0,"image_border_radius":0,"enable_border":false,"border_radius":4,"border_color":"#e2e5e7","border_color_hover":"#2d2d2d","text_position":"left","title":"Title","line-style-on":false,"color_text_col":"#ffffff","color_text_hover":"#3e8cc4","margin_bottom_title":0,"description":"<ul><li>Lorem Ipsum<\/li><li>Lorem Ipsum<\/li><li>Lorem Ipsum<\/li><li>Lorem Ipsum<\/li><li>Lorem Ipsum<\/li><li>Lorem Ipsum<\/li><\/ul>","color_des":"#ffffff","link-button-on":false,"link-button-text":"","link":"","link-button-icon":false,"link-button-padding":"","box_shadow":"none","bx_horizontal_length":0,"bx_vertical_length":3,"bx_blur_radius":8,"bx_spread":0,"bx_opacity":0.2,"bx_inset":"no"}}},"block_order":["image_whMQti","image_wQJKez","image_9QpB3f"],"settings":{"section-id":"features","container":"container","padding_full_width":0,"mg_top_desktop":60,"mg_top_tablet":50,"mg_top_mobile":50,"mg_bottom_desktop":60,"mg_bottom_tablet":50,"mg_bottom_mobile":50,"brands_block_style":"style_1","enable_icons":true,"brand_layout":"grid","brand_bg":"#141006","brand_bg_gradient":"","brand_title":"Title","title_alignment":"center","color_title":"#ffffff","fontsize_title":46,"fontsize_title_mb":16,"mg_bottom_title":25,"enable_border_title":false,"border_color_title":"#051c42","brand_des":"","color_des":"#1d1d1d","fontsize_des":18,"mg_bottom_des":0,"btn_text":"","fontsize_btn":12,"btn_spacing_top":15,"btn_link":"","btn_color":"#ffffff","main_btn_color":"#006cb6","main_btn_color_hover":"#16c7ff","second_butt":false,"sec_btn_text":"","sec_btn_link":"","sec_btn_color":"#ffffff","sec_main_btn_color":"#16c7ff","sec_main_btn_color_hover":"#006cb6","item_distance":15,"title_align":"center","col-radius":7,"brand_rows":"3","col_btn_color":"#ffffff","col_main_btn_color":"#000000","col_main_btn_color_hover":"#919191","fontsize_text":24,"fontsize_text_mb":18,"font_weight_title":"600","enable_arrows":true,"enable_dots":false,"style_position_arrows":"none","position_horizontal_arrow":15,"color_arrow":"","arrow_background":"","arrow_background_gradient":"","arrow_border":"","color_arrow_hover":"","arrow_background_hover":"","arrow_background_gradient_hover":"","arrow_border_hover":"","brand_rows_mb":"1","enable_hover_zoom_image":false}},"testimonial_custom_88BqKW":{"type":"testimonial-custom","blocks":{"testimonials_QMc6FQ":{"type":"testimonials","settings":{"testmonial_name":"Owner Name","testmonial_company":"Company","testmonial_desc":"<p>Testimonial<\/p>","testmonial_feed":"<p>Feedback<\/p>"}},"testimonials_jf7hDQ":{"type":"testimonials","settings":{"testmonial_name":"Owner Name","testmonial_company":"Company","testmonial_desc":"<p>Testimonial<\/p>","testmonial_feed":"<p>Feedback<\/p>"}}},"block_order":["testimonials_QMc6FQ","testimonials_jf7hDQ"],"settings":{"testimonial_bg":"#ffce17"}},"column_grid_exiKmG":{"type":"column-grid","blocks":{"image_GeEMYe":{"type":"image","settings":{"col_bg":"rgba(0,0,0,0)","margin_bottom_image":0,"image_border_radius":0,"enable_border":false,"border_radius":4,"border_color":"#e2e5e7","border_color_hover":"#2d2d2d","text_position":"left","title":"","line-style-on":false,"color_text_col":"#1d1d1d","color_text_hover":"#3e8cc4","margin_bottom_title":0,"description":"","color_des":"#1d1d1d","link-button-on":false,"link-button-text":"","link":"","link-button-icon":false,"link-button-padding":"","box_shadow":"none","bx_horizontal_length":0,"bx_vertical_length":3,"bx_blur_radius":8,"bx_spread":0,"bx_opacity":0.2,"bx_inset":"no"}},"image_cVJEym":{"type":"image","settings":{"col_bg":"rgba(0,0,0,0)","margin_bottom_image":0,"image_border_radius":0,"enable_border":false,"border_radius":4,"border_color":"#e2e5e7","border_color_hover":"#2d2d2d","text_position":"left","title":"","line-style-on":false,"color_text_col":"#1d1d1d","color_text_hover":"#3e8cc4","margin_bottom_title":0,"description":"","color_des":"#1d1d1d","link-button-on":false,"link-button-text":"","link":"","link-button-icon":false,"link-button-padding":"","box_shadow":"none","bx_horizontal_length":0,"bx_vertical_length":3,"bx_blur_radius":8,"bx_spread":0,"bx_opacity":0.2,"bx_inset":"no"}},"image_BM3CJD":{"type":"image","settings":{"col_bg":"rgba(0,0,0,0)","margin_bottom_image":0,"image_border_radius":0,"enable_border":false,"border_radius":4,"border_color":"#e2e5e7","border_color_hover":"#2d2d2d","text_position":"left","title":"","line-style-on":false,"color_text_col":"#1d1d1d","color_text_hover":"#3e8cc4","margin_bottom_title":0,"description":"","color_des":"#1d1d1d","link-button-on":false,"link-button-text":"","link":"","link-button-icon":false,"link-button-padding":"","box_shadow":"none","bx_horizontal_length":0,"bx_vertical_length":3,"bx_blur_radius":8,"bx_spread":0,"bx_opacity":0.2,"bx_inset":"no"}},"image_cQVDDt":{"type":"image","settings":{"col_bg":"rgba(0,0,0,0)","margin_bottom_image":0,"image_border_radius":0,"enable_border":false,"border_radius":4,"border_color":"#e2e5e7","border_color_hover":"#2d2d2d","text_position":"left","title":"","line-style-on":false,"color_text_col":"#1d1d1d","color_text_hover":"#3e8cc4","margin_bottom_title":0,"description":"","color_des":"#1d1d1d","link-button-on":false,"link-button-text":"","link":"","link-button-icon":false,"link-button-padding":"","box_shadow":"none","bx_horizontal_length":0,"bx_vertical_length":3,"bx_blur_radius":8,"bx_spread":0,"bx_opacity":0.2,"bx_inset":"no"}},"image_PHMHnn":{"type":"image","settings":{"col_bg":"rgba(0,0,0,0)","margin_bottom_image":0,"image_border_radius":0,"enable_border":false,"border_radius":4,"border_color":"#e2e5e7","border_color_hover":"#2d2d2d","text_position":"left","title":"","line-style-on":false,"color_text_col":"#1d1d1d","color_text_hover":"#3e8cc4","margin_bottom_title":0,"description":"","color_des":"#1d1d1d","link-button-on":false,"link-button-text":"","link":"","link-button-icon":false,"link-button-padding":"","box_shadow":"none","bx_horizontal_length":0,"bx_vertical_length":3,"bx_blur_radius":8,"bx_spread":0,"bx_opacity":0.2,"bx_inset":"no"}},"image_kJMLdB":{"type":"image","settings":{"col_bg":"rgba(0,0,0,0)","margin_bottom_image":0,"image_border_radius":0,"enable_border":false,"border_radius":4,"border_color":"#e2e5e7","border_color_hover":"#2d2d2d","text_position":"left","title":"","line-style-on":false,"color_text_col":"#1d1d1d","color_text_hover":"#3e8cc4","margin_bottom_title":0,"description":"","color_des":"#1d1d1d","link-button-on":false,"link-button-text":"","link":"","link-button-icon":false,"link-button-padding":"","box_shadow":"none","bx_horizontal_length":0,"bx_vertical_length":3,"bx_blur_radius":8,"bx_spread":0,"bx_opacity":0.2,"bx_inset":"no"}},"image_X9ATQW":{"type":"image","settings":{"col_bg":"rgba(0,0,0,0)","margin_bottom_image":0,"image_border_radius":0,"enable_border":false,"border_radius":4,"border_color":"#e2e5e7","border_color_hover":"#2d2d2d","text_position":"left","title":"","line-style-on":false,"color_text_col":"#1d1d1d","color_text_hover":"#3e8cc4","margin_bottom_title":0,"description":"","color_des":"#1d1d1d","link-button-on":false,"link-button-text":"","link":"","link-button-icon":false,"link-button-padding":"","box_shadow":"none","bx_horizontal_length":0,"bx_vertical_length":3,"bx_blur_radius":8,"bx_spread":0,"bx_opacity":0.2,"bx_inset":"no"}},"image_BnxFwy":{"type":"image","settings":{"col_bg":"rgba(0,0,0,0)","margin_bottom_image":0,"image_border_radius":0,"enable_border":false,"border_radius":4,"border_color":"#e2e5e7","border_color_hover":"#2d2d2d","text_position":"left","title":"","line-style-on":false,"color_text_col":"#1d1d1d","color_text_hover":"#3e8cc4","margin_bottom_title":0,"description":"","color_des":"#1d1d1d","link-button-on":false,"link-button-text":"","link":"","link-button-icon":false,"link-button-padding":"","box_shadow":"none","bx_horizontal_length":0,"bx_vertical_length":3,"bx_blur_radius":8,"bx_spread":0,"bx_opacity":0.2,"bx_inset":"no"}}},"block_order":["image_GeEMYe","image_cVJEym","image_BM3CJD","image_cQVDDt","image_PHMHnn","image_kJMLdB","image_X9ATQW","image_BnxFwy"],"settings":{"section-id":"partners-home","container":"container","padding_full_width":0,"mg_top_desktop":90,"mg_top_tablet":50,"mg_top_mobile":50,"mg_bottom_desktop":50,"mg_bottom_tablet":50,"mg_bottom_mobile":0,"brands_block_style":"style_1","enable_icons":true,"brand_layout":"grid","brand_bg":"rgba(0,0,0,0)","brand_bg_gradient":"","brand_title":"Our Partners","title_alignment":"center","color_title":"#141006","fontsize_title":32,"fontsize_title_mb":16,"mg_bottom_title":50,"enable_border_title":false,"border_color_title":"#051c42","brand_des":"","color_des":"#1d1d1d","fontsize_des":18,"mg_bottom_des":0,"btn_text":"","fontsize_btn":12,"btn_spacing_top":15,"btn_link":"","btn_color":"#ffffff","main_btn_color":"#006cb6","main_btn_color_hover":"#16c7ff","second_butt":false,"sec_btn_text":"","sec_btn_link":"","sec_btn_color":"#ffffff","sec_main_btn_color":"#16c7ff","sec_main_btn_color_hover":"#006cb6","item_distance":15,"title_align":"center","col-radius":7,"brand_rows":"4","col_btn_color":"#ffffff","col_main_btn_color":"#000000","col_main_btn_color_hover":"#919191","fontsize_text":24,"fontsize_text_mb":18,"font_weight_title":"600","enable_arrows":true,"enable_dots":false,"style_position_arrows":"none","position_horizontal_arrow":15,"color_arrow":"","arrow_background":"","arrow_background_gradient":"","arrow_border":"","color_arrow_hover":"","arrow_background_hover":"","arrow_background_gradient_hover":"","arrow_border_hover":"","brand_rows_mb":"1","enable_hover_zoom_image":false}},"custom_cta_PYgJLY":{"type":"custom-cta","settings":{"cta_sec_id":"","fullwidths":false,"margin_top":0,"margin_bottom":0,"padding_top":50,"padding_bottom":80,"cta_text_title":"CTA title","title_margin_bot":20,"cta_texts":"","cta_texts_font_size":18,"cta_texts_color":"#141006","cta_button_text":"Enquire now","cta_button_link":"shopify:\/\/pages\/contact-us","btn_margin_top":25}}},"order":["16321237356a896dad","column_grid_VDzQYy","custom_cta_m8BjgC","17296510480ec9458f","video_block_FFnUpA","column_grid_km3BJi","testimonial_custom_88BqKW","column_grid_exiKmG","custom_cta_PYgJLY"]}